simple_calculator_osama_alhalali/__init__.py
simple_calculator_osama_alhalali/calculator.py
simple_calculator_osama_alhalali-0.1.0.dist-info/licenses/LICENSE
simple_calculator_osama_alhalali-0.1.0.dist-info/METADATA
simple_calculator_osama_alhalali-0.1.0.dist-info/WHEEL
simple_calculator_osama_alhalali-0.1.0.dist-info/top_level.txt
simple_calculator_osama_alhalali-0.1.0.dist-info/RECORD
