Metadata-Version: 2.4
Name: simple-calculator-osama-alhalali
Version: 0.1.0
Summary: حزمة آلة حاسبة بسيطة لعمليات الرياضيات الأساسية.
Home-page: https://github.com/osama-alhalali/simple-calculator
Author: اسامة الحللي
Author-email: osama.alhalali@example.com
Classifier: Programming Language :: Python :: 3
Classifier: License :: OSI Approved :: MIT License
Classifier: Operating System :: OS Independent
Requires-Python: >=3.6
License-File: LICENSE
Dynamic: author
Dynamic: author-email
Dynamic: classifier
Dynamic: description
Dynamic: description-content-type
Dynamic: home-page
Dynamic: license-file
Dynamic: requires-python
Dynamic: summary
